optga/__init__.py
optga/config.py
optga/evaluater.py
optga/optimizer.py
optga/spawner.py
optga/strategy.py
optga/support.py
optga/tools/constraint.py
optga/tools/mate.py
optga/tools/mutate.py
optga/tools/nsga2.py
optga/tools/select.py
optga/tools/sobol.py
optga-0.2.0.dist-info/entry_points.txt
optga-0.2.0.dist-info/WHEEL
optga-0.2.0.dist-info/METADATA
optga-0.2.0.dist-info/RECORD
