Metadata-Version: 2.1
Name: optga
Version: 0.2.0
Summary: Framework to find pareto-optimum inputs of your machine learning models
Author: horoiwa
Author-email: horoiwa195@gmail.com
Requires-Python: >=3.7,<4.0
Classifier: Programming Language :: Python :: 3
Classifier: Programming Language :: Python :: 3.7
Classifier: Programming Language :: Python :: 3.8
Requires-Dist: dataclasses_json (>=0.3.7,<0.4.0)
Requires-Dist: llvmlite (==0.30.0)
Requires-Dist: numba (==0.45.0)
Requires-Dist: numpy (>=1.17,<2.0)
Requires-Dist: pandas (>=0.25.3,<0.26.0)
